[{"imsyak": "03:49", "shubuh": "03:59", "dzuhur": "11:28", "tanggal": "2020-07-01", "terbit": "05:19", "magrib": "17:32", "isya": "18:47", "dhuha": "05:43", "ashr": "14:53"}, {"imsyak": "03:49", "shubuh": "03:59", "dzuhur": "11:28", "tanggal": "2020-07-02", "terbit": "05:19", "magrib": "17:32", "isya": "18:47", "dhuha": "05:43", "ashr": "14:54"}, {"imsyak": "03:50", "shubuh": "04:00", "dzuhur": "11:28", "tanggal": "2020-07-03", "terbit": "05:19", "magrib": "17:33", "isya": "18:47", "dhuha": "05:43", "ashr": "14:54"}, {"imsyak": "03:50", "shubuh": "04:00", "dzuhur": "11:28", "tanggal": "2020-07-04", "terbit": "05:19", "magrib": "17:33", "isya": "18:48", "dhuha": "05:43", "ashr": "14:54"}, {"imsyak": "03:50", "shubuh": "04:00", "dzuhur": "11:28", "tanggal": "2020-07-05", "terbit": "05:20", "magrib": "17:33", "isya": "18:48", "dhuha": "05:44", "ashr": "14:54"}, {"imsyak": "03:50", "shubuh": "04:00", "dzuhur": "11:28", "tanggal": "2020-07-06", "terbit": "05:20", "magrib": "17:33", "isya": "18:48", "dhuha": "05:44", "ashr": "14:54"}, {"imsyak": "03:51", "shubuh": "04:01", "dzuhur": "11:29", "tanggal": "2020-07-07", "terbit": "05:20", "magrib": "17:33", "isya": "18:48", "dhuha": "05:44", "ashr": "14:54"}, {"imsyak": "03:51", "shubuh": "04:01", "dzuhur": "11:29", "tanggal": "2020-07-08", "terbit": "05:20", "magrib": "17:33", "isya": "18:48", "dhuha": "05:44", "ashr": "14:54"}, {"imsyak": "03:51", "shubuh": "04:01", "dzuhur": "11:29", "tanggal": "2020-07-09", "terbit": "05:20", "magrib": "17:34", "isya": "18:48", "dhuha": "05:44", "ashr": "14:54"}, {"imsyak": "03:51", "shubuh": "04:01", "dzuhur": "11:29", "tanggal": "2020-07-10", "terbit": "05:20", "magrib": "17:34", "isya": "18:48", "dhuha": "05:44", "ashr": "14:54"}, {"imsyak": "03:51", "shubuh": "04:01", "dzuhur": "11:29", "tanggal": "2020-07-11", "terbit": "05:21", "magrib": "17:34", "isya": "18:48", "dhuha": "05:45", "ashr": "14:55"}, {"imsyak": "03:52", "shubuh": "04:02", "dzuhur": "11:29", "tanggal": "2020-07-12", "terbit": "05:21", "magrib": "17:34", "isya": "18:48", "dhuha": "05:45", "ashr": "14:55"}, {"imsyak": "03:52", "shubuh": "04:02", "dzuhur": "11:29", "tanggal": "2020-07-13", "terbit": "05:21", "magrib": "17:34", "isya": "18:48", "dhuha": "05:45", "ashr": "14:55"}, {"imsyak": "03:52", "shubuh": "04:02", "dzuhur": "11:30", "tanggal": "2020-07-14", "terbit": "05:21", "magrib": "17:34", "isya": "18:48", "dhuha": "05:45", "ashr": "14:55"}, {"imsyak": "03:52", "shubuh": "04:02", "dzuhur": "11:30", "tanggal": "2020-07-15", "terbit": "05:21", "magrib": "17:34", "isya": "18:48", "dhuha": "05:45", "ashr": "14:55"}, {"imsyak": "03:53", "shubuh": "04:03", "dzuhur": "11:30", "tanggal": "2020-07-16", "terbit": "05:21", "magrib": "17:34", "isya": "18:48", "dhuha": "05:45", "ashr": "14:55"}, {"imsyak": "03:53", "shubuh": "04:03", "dzuhur": "11:30", "tanggal": "2020-07-17", "terbit": "05:21", "magrib": "17:34", "isya": "18:48", "dhuha": "05:45", "ashr": "14:55"}, {"imsyak": "03:53", "shubuh": "04:03", "dzuhur": "11:30", "tanggal": "2020-07-18", "terbit": "05:21", "magrib": "17:34", "isya": "18:48", "dhuha": "05:45", "ashr": "14:55"}, {"imsyak": "03:53", "shubuh": "04:03", "dzuhur": "11:30", "tanggal": "2020-07-19", "terbit": "05:22", "magrib": "17:34", "isya": "18:48", "dhuha": "05:46", "ashr": "14:55"}, {"imsyak": "03:53", "shubuh": "04:03", "dzuhur": "11:30", "tanggal": "2020-07-20", "terbit": "05:22", "magrib": "17:35", "isya": "18:48", "dhuha": "05:46", "ashr": "14:55"}, {"imsyak": "03:53", "shubuh": "04:03", "dzuhur": "11:30", "tanggal": "2020-07-21", "terbit": "05:22", "magrib": "17:35", "isya": "18:48", "dhuha": "05:46", "ashr": "14:55"}, {"imsyak": "03:54", "shubuh": "04:04", "dzuhur": "11:30", "tanggal": "2020-07-22", "terbit": "05:22", "magrib": "17:35", "isya": "18:48", "dhuha": "05:46", "ashr": "14:54"}, {"imsyak": "03:54", "shubuh": "04:04", "dzuhur": "11:30", "tanggal": "2020-07-23", "terbit": "05:22", "magrib": "17:35", "isya": "18:48", "dhuha": "05:46", "ashr": "14:54"}, {"imsyak": "03:54", "shubuh": "04:04", "dzuhur": "11:30", "tanggal": "2020-07-24", "terbit": "05:22", "magrib": "17:35", "isya": "18:48", "dhuha": "05:46", "ashr": "14:54"}, {"imsyak": "03:54", "shubuh": "04:04", "dzuhur": "11:30", "tanggal": "2020-07-25", "terbit": "05:22", "magrib": "17:35", "isya": "18:48", "dhuha": "05:46", "ashr": "14:54"}, {"imsyak": "03:54", "shubuh": "04:04", "dzuhur": "11:30", "tanggal": "2020-07-26", "terbit": "05:22", "magrib": "17:35", "isya": "18:48", "dhuha": "05:46", "ashr": "14:54"}, {"imsyak": "03:54", "shubuh": "04:04", "dzuhur": "11:30", "tanggal": "2020-07-27", "terbit": "05:22", "magrib": "17:35", "isya": "18:47", "dhuha": "05:46", "ashr": "14:54"}, {"imsyak": "03:55", "shubuh": "04:05", "dzuhur": "11:30", "tanggal": "2020-07-28", "terbit": "05:22", "magrib": "17:35", "isya": "18:47", "dhuha": "05:46", "ashr": "14:54"}, {"imsyak": "03:55", "shubuh": "04:05", "dzuhur": "11:30", "tanggal": "2020-07-29", "terbit": "05:22", "magrib": "17:34", "isya": "18:47", "dhuha": "05:46", "ashr": "14:53"}, {"imsyak": "03:55", "shubuh": "04:05", "dzuhur": "11:30", "tanggal": "2020-07-30", "terbit": "05:22", "magrib": "17:34", "isya": "18:47", "dhuha": "05:46", "ashr": "14:53"}, {"imsyak": "03:55", "shubuh": "04:05", "dzuhur": "11:30", "tanggal": "2020-07-31", "terbit": "05:22", "magrib": "17:34", "isya": "18:47", "dhuha": "05:46", "ashr": "14:53"}]