[{"tanggal": "2021-12-01", "imsyak": "04:24", "shubuh": "04:34", "terbit": "05:53", "dhuha": "06:17", "dzuhur": "12:06", "ashr": "15:31", "magrib": "18:15", "isya": "19:29"}, {"tanggal": "2021-12-02", "imsyak": "04:24", "shubuh": "04:34", "terbit": "05:53", "dhuha": "06:17", "dzuhur": "12:06", "ashr": "15:32", "magrib": "18:15", "isya": "19:30"}, {"tanggal": "2021-12-03", "imsyak": "04:24", "shubuh": "04:34", "terbit": "05:54", "dhuha": "06:18", "dzuhur": "12:07", "ashr": "15:32", "magrib": "18:16", "isya": "19:30"}, {"tanggal": "2021-12-04", "imsyak": "04:24", "shubuh": "04:34", "terbit": "05:54", "dhuha": "06:18", "dzuhur": "12:07", "ashr": "15:33", "magrib": "18:16", "isya": "19:31"}, {"tanggal": "2021-12-05", "imsyak": "04:25", "shubuh": "04:35", "terbit": "05:54", "dhuha": "06:18", "dzuhur": "12:07", "ashr": "15:33", "magrib": "18:16", "isya": "19:31"}, {"tanggal": "2021-12-06", "imsyak": "04:25", "shubuh": "04:35", "terbit": "05:55", "dhuha": "06:19", "dzuhur": "12:08", "ashr": "15:34", "magrib": "18:17", "isya": "19:32"}, {"tanggal": "2021-12-07", "imsyak": "04:25", "shubuh": "04:35", "terbit": "05:55", "dhuha": "06:19", "dzuhur": "12:08", "ashr": "15:34", "magrib": "18:17", "isya": "19:32"}, {"tanggal": "2021-12-08", "imsyak": "04:25", "shubuh": "04:35", "terbit": "05:55", "dhuha": "06:19", "dzuhur": "12:09", "ashr": "15:35", "magrib": "18:18", "isya": "19:33"}, {"tanggal": "2021-12-09", "imsyak": "04:26", "shubuh": "04:36", "terbit": "05:56", "dhuha": "06:20", "dzuhur": "12:09", "ashr": "15:35", "magrib": "18:18", "isya": "19:33"}, {"tanggal": "2021-12-10", "imsyak": "04:26", "shubuh": "04:36", "terbit": "05:56", "dhuha": "06:20", "dzuhur": "12:09", "ashr": "15:36", "magrib": "18:19", "isya": "19:34"}, {"tanggal": "2021-12-11", "imsyak": "04:26", "shubuh": "04:36", "terbit": "05:57", "dhuha": "06:21", "dzuhur": "12:10", "ashr": "15:36", "magrib": "18:19", "isya": "19:34"}, {"tanggal": "2021-12-12", "imsyak": "04:27", "shubuh": "04:37", "terbit": "05:57", "dhuha": "06:21", "dzuhur": "12:10", "ashr": "15:37", "magrib": "18:20", "isya": "19:35"}, {"tanggal": "2021-12-13", "imsyak": "04:27", "shubuh": "04:37", "terbit": "05:57", "dhuha": "06:21", "dzuhur": "12:11", "ashr": "15:37", "magrib": "18:20", "isya": "19:36"}, {"tanggal": "2021-12-14", "imsyak": "04:28", "shubuh": "04:38", "terbit": "05:58", "dhuha": "06:22", "dzuhur": "12:11", "ashr": "15:38", "magrib": "18:21", "isya": "19:36"}, {"tanggal": "2021-12-15", "imsyak": "04:28", "shubuh": "04:38", "terbit": "05:58", "dhuha": "06:22", "dzuhur": "12:12", "ashr": "15:38", "magrib": "18:21", "isya": "19:37"}, {"tanggal": "2021-12-16", "imsyak": "04:28", "shubuh": "04:38", "terbit": "05:59", "dhuha": "06:23", "dzuhur": "12:12", "ashr": "15:39", "magrib": "18:22", "isya": "19:37"}, {"tanggal": "2021-12-17", "imsyak": "04:29", "shubuh": "04:39", "terbit": "05:59", "dhuha": "06:23", "dzuhur": "12:13", "ashr": "15:40", "magrib": "18:22", "isya": "19:38"}, {"tanggal": "2021-12-18", "imsyak": "04:29", "shubuh": "04:39", "terbit": "06:00", "dhuha": "06:24", "dzuhur": "12:13", "ashr": "15:40", "magrib": "18:23", "isya": "19:38"}, {"tanggal": "2021-12-19", "imsyak": "04:30", "shubuh": "04:40", "terbit": "06:00", "dhuha": "06:24", "dzuhur": "12:14", "ashr": "15:41", "magrib": "18:23", "isya": "19:39"}, {"tanggal": "2021-12-20", "imsyak": "04:30", "shubuh": "04:40", "terbit": "06:01", "dhuha": "06:25", "dzuhur": "12:14", "ashr": "15:41", "magrib": "18:24", "isya": "19:39"}, {"tanggal": "2021-12-21", "imsyak": "04:31", "shubuh": "04:41", "terbit": "06:01", "dhuha": "06:25", "dzuhur": "12:15", "ashr": "15:42", "magrib": "18:24", "isya": "19:40"}, {"tanggal": "2021-12-22", "imsyak": "04:31", "shubuh": "04:41", "terbit": "06:02", "dhuha": "06:26", "dzuhur": "12:15", "ashr": "15:42", "magrib": "18:25", "isya": "19:40"}, {"tanggal": "2021-12-23", "imsyak": "04:32", "shubuh": "04:42", "terbit": "06:02", "dhuha": "06:26", "dzuhur": "12:16", "ashr": "15:43", "magrib": "18:25", "isya": "19:41"}, {"tanggal": "2021-12-24", "imsyak": "04:32", "shubuh": "04:42", "terbit": "06:03", "dhuha": "06:27", "dzuhur": "12:16", "ashr": "15:43", "magrib": "18:26", "isya": "19:41"}, {"tanggal": "2021-12-25", "imsyak": "04:33", "shubuh": "04:43", "terbit": "06:03", "dhuha": "06:27", "dzuhur": "12:17", "ashr": "15:44", "magrib": "18:26", "isya": "19:42"}, {"tanggal": "2021-12-26", "imsyak": "04:33", "shubuh": "04:43", "terbit": "06:04", "dhuha": "06:28", "dzuhur": "12:17", "ashr": "15:44", "magrib": "18:27", "isya": "19:42"}, {"tanggal": "2021-12-27", "imsyak": "04:34", "shubuh": "04:44", "terbit": "06:04", "dhuha": "06:28", "dzuhur": "12:18", "ashr": "15:45", "magrib": "18:27", "isya": "19:43"}, {"tanggal": "2021-12-28", "imsyak": "04:34", "shubuh": "04:44", "terbit": "06:05", "dhuha": "06:29", "dzuhur": "12:18", "ashr": "15:45", "magrib": "18:28", "isya": "19:43"}, {"tanggal": "2021-12-29", "imsyak": "04:35", "shubuh": "04:45", "terbit": "06:05", "dhuha": "06:29", "dzuhur": "12:19", "ashr": "15:45", "magrib": "18:28", "isya": "19:44"}, {"tanggal": "2021-12-30", "imsyak": "04:35", "shubuh": "04:45", "terbit": "06:06", "dhuha": "06:30", "dzuhur": "12:19", "ashr": "15:46", "magrib": "18:29", "isya": "19:44"}, {"tanggal": "2021-12-31", "imsyak": "04:36", "shubuh": "04:46", "terbit": "06:06", "dhuha": "06:30", "dzuhur": "12:20", "ashr": "15:46", "magrib": "18:29", "isya": "19:44"}]